django_triflesoft_organizations-0.3.1510011648.dist-info/DESCRIPTION.rst
django_triflesoft_organizations-0.3.1510011648.dist-info/METADATA
django_triflesoft_organizations-0.3.1510011648.dist-info/RECORD
django_triflesoft_organizations-0.3.1510011648.dist-info/WHEEL
django_triflesoft_organizations-0.3.1510011648.dist-info/metadata.json
django_triflesoft_organizations-0.3.1510011648.dist-info/top_level.txt
organizations/__init__.py
organizations/admin.py
organizations/models.py
