Metadata-Version: 2.0
Name: django-triflesoft-organizations
Version: 0.3.1510011648
Summary: Django organizations models by TrifleSoft
Home-page: https://bitbucket.org/triflesoft/django-organizations
Author: TrifleSoft LLC
Author-email: support@triflesoft.org
License: BSD
Keywords: django organizations triflesoft
Platform: UNKNOWN
Classifier: Development Status :: 5 - Production/Stable
Classifier: Environment :: No Input/Output (Daemon)
Classifier: Framework :: Django
Classifier: Framework :: Django :: 1.7
Classifier: Intended Audience :: Developers
Classifier: License :: OSI Approved :: BSD License
Classifier: Operating System :: POSIX :: Linux
Classifier: Programming Language :: Python :: 3 :: Only
Classifier: Programming Language :: Python :: 3.4
Requires-Dist: django
Requires-Dist: django-triflesoft-localization
Requires-Dist: django-triflesoft-locations
